[{"charIdx": 0, "char": "ب", "start": 0.988, "end": 1.111, "duration": 122.2, "wordIdx": 0}, {"charIdx": 1, "char": "س", "start": 1.111, "end": 1.213, "duration": 101.9, "wordIdx": 0}, {"charIdx": 2, "char": "م", "start": 1.213, "end": 1.294, "duration": 81.5, "wordIdx": 0}, {"charIdx": 0, "char": "ا", "start": 1.48, "end": 1.564, "duration": 83.7, "wordIdx": 1}, {"charIdx": 1, "char": "ل", "start": 1.564, "end": 1.648, "duration": 83.7, "wordIdx": 1}, {"charIdx": 2, "char": "ل", "start": 1.648, "end": 1.752, "duration": 104.6, "wordIdx": 1}, {"charIdx": 3, "char": "ه", "start": 1.752, "end": 1.815, "duration": 62.7, "wordIdx": 1}, {"charIdx": 0, "char": "ا", "start": 2.019, "end": 2.163, "duration": 143.8, "wordIdx": 2}, {"charIdx": 1, "char": "ل", "start": 2.163, "end": 2.307, "duration": 143.8, "wordIdx": 2}, {"charIdx": 2, "char": "ر", "start": 2.307, "end": 2.43, "duration": 123.2, "wordIdx": 2}, {"charIdx": 3, "char": "ح", "start": 2.43, "end": 2.594, "duration": 164.3, "wordIdx": 2}, {"charIdx": 4, "char": "م", "start": 2.594, "end": 2.697, "duration": 102.7, "wordIdx": 2}, {"charIdx": 5, "char": "ن", "start": 2.557, "end": 2.697, "duration": 140.3, "wordIdx": 2}, {"charIdx": 0, "char": "ا", "start": 2.861, "end": 3.067, "duration": 205.7, "wordIdx": 3}, {"charIdx": 1, "char": "ل", "start": 3.067, "end": 3.211, "duration": 144.0, "wordIdx": 3}, {"charIdx": 2, "char": "ر", "start": 3.211, "end": 3.355, "duration": 144.0, "wordIdx": 3}, {"charIdx": 3, "char": "ح", "start": 3.355, "end": 3.478, "duration": 123.4, "wordIdx": 3}, {"charIdx": 4, "char": "ي", "start": 3.224, "end": 3.351, "duration": 126.8, "wordIdx": 3}, {"charIdx": 5, "char": "م", "start": 3.351, "end": 3.478, "duration": 126.8, "wordIdx": 3}, {"charIdx": 0, "char": "و", "start": 3.661, "end": 3.825, "duration": 164.2, "wordIdx": 4}, {"charIdx": 1, "char": "ا", "start": 3.825, "end": 4.031, "duration": 205.2, "wordIdx": 4}, {"charIdx": 2, "char": "ل", "start": 4.031, "end": 4.215, "duration": 184.7, "wordIdx": 4}, {"charIdx": 3, "char": "ل", "start": 4.215, "end": 4.297, "duration": 82.1, "wordIdx": 4}, {"charIdx": 4, "char": "ي", "start": 4.297, "end": 4.4, "duration": 102.6, "wordIdx": 4}, {"charIdx": 5, "char": "ل", "start": 4.256, "end": 4.4, "duration": 143.7, "wordIdx": 4}, {"charIdx": 0, "char": "إ", "start": 4.42, "end": 4.609, "duration": 188.6, "wordIdx": 5}, {"charIdx": 1, "char": "ذ", "start": 4.609, "end": 4.734, "duration": 125.7, "wordIdx": 5}, {"charIdx": 2, "char": "ا", "start": 4.734, "end": 4.881, "duration": 146.7, "wordIdx": 5}, {"charIdx": 0, "char": "ي", "start": 4.961, "end": 5.023, "duration": 61.7, "wordIdx": 6}, {"charIdx": 1, "char": "غ", "start": 5.023, "end": 5.146, "duration": 123.5, "wordIdx": 6}, {"charIdx": 2, "char": "ش", "start": 5.146, "end": 5.27, "duration": 123.5, "wordIdx": 6}, {"charIdx": 3, "char": "ي", "start": 5.27, "end": 5.29, "duration": 20.6, "wordIdx": 6}, {"charIdx": 0, "char": "و", "start": 5.843, "end": 5.924, "duration": 81.2, "wordIdx": 7}, {"charIdx": 1, "char": "ا", "start": 5.924, "end": 6.046, "duration": 121.8, "wordIdx": 7}, {"charIdx": 2, "char": "ل", "start": 6.046, "end": 6.594, "duration": 548.1, "wordIdx": 7}, {"charIdx": 3, "char": "ن", "start": 6.594, "end": 6.817, "duration": 223.3, "wordIdx": 7}, {"charIdx": 4, "char": "ه", "start": 6.817, "end": 6.959, "duration": 142.1, "wordIdx": 7}, {"charIdx": 5, "char": "ا", "start": 6.959, "end": 7.223, "duration": 263.9, "wordIdx": 7}, {"charIdx": 6, "char": "ر", "start": 7.223, "end": 7.406, "duration": 182.7, "wordIdx": 7}, {"charIdx": 0, "char": "إ", "start": 7.448, "end": 7.637, "duration": 189.0, "wordIdx": 8}, {"charIdx": 1, "char": "ذ", "start": 7.637, "end": 7.742, "duration": 105.0, "wordIdx": 8}, {"charIdx": 2, "char": "ا", "start": 7.742, "end": 7.847, "duration": 105.0, "wordIdx": 8}, {"charIdx": 0, "char": "ت", "start": 8.049, "end": 8.191, "duration": 142.2, "wordIdx": 9}, {"charIdx": 1, "char": "ج", "start": 8.191, "end": 8.292, "duration": 101.6, "wordIdx": 9}, {"charIdx": 2, "char": "ل", "start": 8.292, "end": 8.394, "duration": 101.6, "wordIdx": 9}, {"charIdx": 3, "char": "ي", "start": 8.394, "end": 8.557, "duration": 162.6, "wordIdx": 9}, {"charIdx": 0, "char": "و", "start": 9.74, "end": 9.825, "duration": 84.7, "wordIdx": 10}, {"charIdx": 1, "char": "م", "start": 9.825, "end": 9.888, "duration": 63.5, "wordIdx": 10}, {"charIdx": 2, "char": "ا", "start": 9.888, "end": 9.952, "duration": 63.5, "wordIdx": 10}, {"charIdx": 0, "char": "خ", "start": 10.254, "end": 10.522, "duration": 268.4, "wordIdx": 11}, {"charIdx": 1, "char": "ل", "start": 10.522, "end": 10.626, "duration": 103.2, "wordIdx": 11}, {"charIdx": 2, "char": "ق", "start": 10.626, "end": 10.77, "duration": 144.5, "wordIdx": 11}, {"charIdx": 0, "char": "ا", "start": 10.935, "end": 11.017, "duration": 82.7, "wordIdx": 12}, {"charIdx": 1, "char": "ل", "start": 11.017, "end": 11.059, "duration": 41.4, "wordIdx": 12}, {"charIdx": 2, "char": "ذ", "start": 11.059, "end": 11.203, "duration": 144.7, "wordIdx": 12}, {"charIdx": 3, "char": "ك", "start": 11.203, "end": 11.431, "duration": 227.5, "wordIdx": 12}, {"charIdx": 4, "char": "ر", "start": 11.431, "end": 11.514, "duration": 82.7, "wordIdx": 12}, {"charIdx": 0, "char": "و", "start": 11.615, "end": 11.655, "duration": 40.1, "wordIdx": 13}, {"charIdx": 1, "char": "ا", "start": 11.655, "end": 11.755, "duration": 100.2, "wordIdx": 13}, {"charIdx": 2, "char": "ل", "start": 11.755, "end": 11.936, "duration": 180.4, "wordIdx": 13}, {"charIdx": 3, "char": "أ", "start": 11.936, "end": 12.898, "duration": 962.2, "wordIdx": 13}, {"charIdx": 4, "char": "ن", "start": 12.898, "end": 13.159, "duration": 260.6, "wordIdx": 13}, {"charIdx": 5, "char": "ف", "start": 13.159, "end": 13.339, "duration": 180.4, "wordIdx": 13}, {"charIdx": 6, "char": "ي", "start": 13.339, "end": 14.201, "duration": 862.0, "wordIdx": 13}, {"charIdx": 0, "char": "إ", "start": 15.0, "end": 15.123, "duration": 123.5, "wordIdx": 14}, {"charIdx": 1, "char": "ن", "start": 14.732, "end": 15.123, "duration": 391.0, "wordIdx": 14}, {"charIdx": 0, "char": "س", "start": 15.284, "end": 15.407, "duration": 123.2, "wordIdx": 15}, {"charIdx": 1, "char": "ع", "start": 15.407, "end": 15.551, "duration": 143.8, "wordIdx": 15}, {"charIdx": 2, "char": "ي", "start": 15.551, "end": 15.653, "duration": 102.7, "wordIdx": 15}, {"charIdx": 3, "char": "ك", "start": 15.653, "end": 15.817, "duration": 164.3, "wordIdx": 15}, {"charIdx": 4, "char": "م", "start": 15.817, "end": 15.92, "duration": 102.7, "wordIdx": 15}, {"charIdx": 0, "char": "ل", "start": 16.368, "end": 16.815, "duration": 446.9, "wordIdx": 16}, {"charIdx": 1, "char": "ش", "start": 16.815, "end": 16.977, "duration": 162.5, "wordIdx": 16}, {"charIdx": 2, "char": "ت", "start": 16.977, "end": 17.668, "duration": 690.7, "wordIdx": 16}, {"charIdx": 3, "char": "ي", "start": 17.297, "end": 17.668, "duration": 370.8, "wordIdx": 16}, {"charIdx": 0, "char": "ف", "start": 17.83, "end": 18.012, "duration": 181.8, "wordIdx": 17}, {"charIdx": 1, "char": "أ", "start": 18.012, "end": 18.294, "duration": 282.8, "wordIdx": 17}, {"charIdx": 2, "char": "م", "start": 18.294, "end": 18.618, "duration": 323.2, "wordIdx": 17}, {"charIdx": 3, "char": "ا", "start": 18.618, "end": 18.779, "duration": 161.6, "wordIdx": 17}, {"charIdx": 0, "char": "م", "start": 20.054, "end": 20.118, "duration": 64.6, "wordIdx": 18}, {"charIdx": 1, "char": "ن", "start": 20.118, "end": 20.161, "duration": 43.1, "wordIdx": 18}, {"charIdx": 0, "char": "أ", "start": 20.493, "end": 20.596, "duration": 103.0, "wordIdx": 19}, {"charIdx": 1, "char": "ع", "start": 20.596, "end": 20.885, "duration": 288.4, "wordIdx": 19}, {"charIdx": 2, "char": "ط", "start": 20.885, "end": 21.008, "duration": 123.6, "wordIdx": 19}, {"charIdx": 3, "char": "ي", "start": 21.008, "end": 21.173, "duration": 164.8, "wordIdx": 19}, {"charIdx": 0, "char": "و", "start": 21.253, "end": 21.354, "duration": 101.5, "wordIdx": 20}, {"charIdx": 1, "char": "ا", "start": 21.354, "end": 21.415, "duration": 60.9, "wordIdx": 20}, {"charIdx": 2, "char": "ت", "start": 21.415, "end": 21.598, "duration": 182.7, "wordIdx": 20}, {"charIdx": 3, "char": "ق", "start": 21.598, "end": 21.882, "duration": 284.2, "wordIdx": 20}, {"charIdx": 4, "char": "ي", "start": 21.882, "end": 22.024, "duration": 142.1, "wordIdx": 20}, {"charIdx": 0, "char": "و", "start": 22.836, "end": 22.897, "duration": 61.3, "wordIdx": 21}, {"charIdx": 1, "char": "ص", "start": 22.897, "end": 23.0, "duration": 102.2, "wordIdx": 21}, {"charIdx": 2, "char": "د", "start": 23.0, "end": 23.388, "duration": 388.5, "wordIdx": 21}, {"charIdx": 3, "char": "ق", "start": 23.388, "end": 23.47, "duration": 81.8, "wordIdx": 21}, {"charIdx": 0, "char": "ب", "start": 23.917, "end": 24.018, "duration": 101.2, "wordIdx": 22}, {"charIdx": 1, "char": "ا", "start": 24.018, "end": 24.261, "duration": 242.9, "wordIdx": 22}, {"charIdx": 2, "char": "ل", "start": 24.261, "end": 24.403, "duration": 141.7, "wordIdx": 22}, {"charIdx": 3, "char": "ح", "start": 24.403, "end": 24.565, "duration": 162.0, "wordIdx": 22}, {"charIdx": 4, "char": "س", "start": 24.565, "end": 24.687, "duration": 121.5, "wordIdx": 22}, {"charIdx": 5, "char": "ن", "start": 24.687, "end": 24.848, "duration": 162.0, "wordIdx": 22}, {"charIdx": 0, "char": "ف", "start": 25.82, "end": 25.921, "duration": 101.3, "wordIdx": 23}, {"charIdx": 1, "char": "س", "start": 25.921, "end": 25.942, "duration": 20.3, "wordIdx": 23}, {"charIdx": 2, "char": "ن", "start": 25.942, "end": 26.002, "duration": 60.7, "wordIdx": 23}, {"charIdx": 3, "char": "ي", "start": 26.002, "end": 26.205, "duration": 202.5, "wordIdx": 23}, {"charIdx": 4, "char": "س", "start": 26.205, "end": 26.407, "duration": 202.5, "wordIdx": 23}, {"charIdx": 5, "char": "ر", "start": 26.407, "end": 26.772, "duration": 364.5, "wordIdx": 23}, {"charIdx": 6, "char": "ه", "start": 26.772, "end": 27.035, "duration": 263.2, "wordIdx": 23}, {"charIdx": 0, "char": "ل", "start": 28.006, "end": 28.107, "duration": 101.4, "wordIdx": 24}, {"charIdx": 1, "char": "ل", "start": 28.107, "end": 28.412, "duration": 304.3, "wordIdx": 24}, {"charIdx": 2, "char": "ي", "start": 28.412, "end": 28.554, "duration": 142.0, "wordIdx": 24}, {"charIdx": 3, "char": "س", "start": 28.554, "end": 28.696, "duration": 142.0, "wordIdx": 24}, {"charIdx": 4, "char": "ر", "start": 28.696, "end": 28.939, "duration": 243.4, "wordIdx": 24}, {"charIdx": 0, "char": "و", "start": 29.526, "end": 29.709, "duration": 183.0, "wordIdx": 25}, {"charIdx": 1, "char": "أ", "start": 29.709, "end": 30.359, "duration": 650.5, "wordIdx": 25}, {"charIdx": 2, "char": "م", "start": 30.359, "end": 30.42, "duration": 61.0, "wordIdx": 25}, {"charIdx": 3, "char": "ا", "start": 30.42, "end": 30.563, "duration": 142.3, "wordIdx": 25}, {"charIdx": 0, "char": "م", "start": 31.151, "end": 31.212, "duration": 61.3, "wordIdx": 26}, {"charIdx": 1, "char": "ن", "start": 31.212, "end": 31.314, "duration": 102.2, "wordIdx": 26}, {"charIdx": 0, "char": "ب", "start": 32.294, "end": 32.481, "duration": 187.3, "wordIdx": 27}, {"charIdx": 1, "char": "خ", "start": 32.481, "end": 32.585, "duration": 104.0, "wordIdx": 27}, {"charIdx": 2, "char": "ل", "start": 32.585, "end": 32.669, "duration": 83.2, "wordIdx": 27}, {"charIdx": 0, "char": "و", "start": 32.974, "end": 33.157, "duration": 183.2, "wordIdx": 28}, {"charIdx": 1, "char": "ا", "start": 33.157, "end": 33.259, "duration": 101.8, "wordIdx": 28}, {"charIdx": 2, "char": "س", "start": 33.259, "end": 33.422, "duration": 162.8, "wordIdx": 28}, {"charIdx": 3, "char": "ت", "start": 33.422, "end": 33.646, "duration": 223.9, "wordIdx": 28}, {"charIdx": 4, "char": "غ", "start": 33.646, "end": 33.788, "duration": 142.5, "wordIdx": 28}, {"charIdx": 5, "char": "ن", "start": 33.788, "end": 33.992, "duration": 203.6, "wordIdx": 28}, {"charIdx": 6, "char": "ي", "start": 33.82, "end": 33.992, "duration": 171.6, "wordIdx": 28}, {"charIdx": 0, "char": "و", "start": 34.073, "end": 34.114, "duration": 40.8, "wordIdx": 29}, {"charIdx": 1, "char": "ك", "start": 34.114, "end": 34.175, "duration": 61.2, "wordIdx": 29}, {"charIdx": 2, "char": "ذ", "start": 34.175, "end": 34.297, "duration": 122.4, "wordIdx": 29}, {"charIdx": 3, "char": "ب", "start": 34.297, "end": 34.44, "duration": 142.8, "wordIdx": 29}, {"charIdx": 0, "char": "ب", "start": 35.315, "end": 35.437, "duration": 121.9, "wordIdx": 30}, {"charIdx": 1, "char": "ا", "start": 35.437, "end": 35.518, "duration": 81.2, "wordIdx": 30}, {"charIdx": 2, "char": "ل", "start": 35.518, "end": 35.579, "duration": 60.9, "wordIdx": 30}, {"charIdx": 3, "char": "ح", "start": 35.579, "end": 35.62, "duration": 40.6, "wordIdx": 30}, {"charIdx": 4, "char": "س", "start": 35.62, "end": 35.762, "duration": 142.2, "wordIdx": 30}, {"charIdx": 5, "char": "ن", "start": 35.762, "end": 35.884, "duration": 121.9, "wordIdx": 30}, {"charIdx": 0, "char": "ف", "start": 36.797, "end": 36.837, "duration": 40.4, "wordIdx": 31}, {"charIdx": 1, "char": "س", "start": 36.837, "end": 36.918, "duration": 80.9, "wordIdx": 31}, {"charIdx": 2, "char": "ن", "start": 36.918, "end": 36.999, "duration": 80.9, "wordIdx": 31}, {"charIdx": 3, "char": "ي", "start": 36.999, "end": 37.12, "duration": 121.3, "wordIdx": 31}, {"charIdx": 4, "char": "س", "start": 37.12, "end": 37.242, "duration": 121.3, "wordIdx": 31}, {"charIdx": 5, "char": "ر", "start": 37.242, "end": 37.323, "duration": 80.9, "wordIdx": 31}, {"charIdx": 6, "char": "ه", "start": 37.323, "end": 37.424, "duration": 101.1, "wordIdx": 31}, {"charIdx": 0, "char": "ل", "start": 39.401, "end": 39.726, "duration": 325.0, "wordIdx": 32}, {"charIdx": 1, "char": "ل", "start": 39.726, "end": 39.868, "duration": 142.2, "wordIdx": 32}, {"charIdx": 2, "char": "ع", "start": 39.868, "end": 40.01, "duration": 142.2, "wordIdx": 32}, {"charIdx": 3, "char": "س", "start": 40.01, "end": 40.843, "duration": 832.7, "wordIdx": 32}, {"charIdx": 4, "char": "ر", "start": 40.542, "end": 40.843, "duration": 300.6, "wordIdx": 32}, {"charIdx": 0, "char": "و", "start": 40.923, "end": 41.11, "duration": 187.0, "wordIdx": 33}, {"charIdx": 1, "char": "م", "start": 41.11, "end": 41.255, "duration": 145.4, "wordIdx": 33}, {"charIdx": 2, "char": "ا", "start": 41.255, "end": 41.484, "duration": 228.6, "wordIdx": 33}, {"charIdx": 0, "char": "ي", "start": 41.504, "end": 41.648, "duration": 144.5, "wordIdx": 34}, {"charIdx": 1, "char": "غ", "start": 41.648, "end": 41.834, "duration": 185.7, "wordIdx": 34}, {"charIdx": 2, "char": "ن", "start": 41.834, "end": 41.999, "duration": 165.1, "wordIdx": 34}, {"charIdx": 3, "char": "ي", "start": 41.999, "end": 42.185, "duration": 185.7, "wordIdx": 34}, {"charIdx": 0, "char": "ع", "start": 42.265, "end": 42.431, "duration": 165.8, "wordIdx": 35}, {"charIdx": 1, "char": "ن", "start": 42.431, "end": 42.617, "duration": 186.5, "wordIdx": 35}, {"charIdx": 2, "char": "ه", "start": 42.617, "end": 42.866, "duration": 248.7, "wordIdx": 35}, {"charIdx": 0, "char": "م", "start": 42.886, "end": 42.987, "duration": 101.1, "wordIdx": 36}, {"charIdx": 1, "char": "ا", "start": 42.987, "end": 43.23, "duration": 242.6, "wordIdx": 36}, {"charIdx": 2, "char": "ل", "start": 43.23, "end": 43.472, "duration": 242.6, "wordIdx": 36}, {"charIdx": 3, "char": "ه", "start": 43.472, "end": 43.675, "duration": 202.2, "wordIdx": 36}, {"charIdx": 0, "char": "إ", "start": 45.235, "end": 45.382, "duration": 147.0, "wordIdx": 37}, {"charIdx": 1, "char": "ذ", "start": 45.382, "end": 45.55, "duration": 168.0, "wordIdx": 37}, {"charIdx": 2, "char": "ا", "start": 45.403, "end": 45.55, "duration": 147.0, "wordIdx": 37}, {"charIdx": 0, "char": "ت", "start": 45.75, "end": 45.892, "duration": 142.3, "wordIdx": 38}, {"charIdx": 1, "char": "ر", "start": 45.892, "end": 46.319, "duration": 426.8, "wordIdx": 38}, {"charIdx": 2, "char": "د", "start": 46.319, "end": 46.482, "duration": 162.6, "wordIdx": 38}, {"charIdx": 3, "char": "د", "start": 46.482, "end": 47.132, "duration": 650.4, "wordIdx": 38}, {"charIdx": 0, "char": "إ", "start": 47.356, "end": 48.533, "duration": 1177.4, "wordIdx": 39}, {"charIdx": 1, "char": "ن", "start": 48.533, "end": 48.655, "duration": 121.8, "wordIdx": 39}, {"charIdx": 0, "char": "ع", "start": 48.96, "end": 49.062, "duration": 102.1, "wordIdx": 40}, {"charIdx": 1, "char": "ل", "start": 49.062, "end": 49.246, "duration": 183.8, "wordIdx": 40}, {"charIdx": 2, "char": "ي", "start": 49.246, "end": 49.41, "duration": 163.4, "wordIdx": 40}, {"charIdx": 3, "char": "ن", "start": 49.41, "end": 49.532, "duration": 122.5, "wordIdx": 40}, {"charIdx": 4, "char": "ا", "start": 49.532, "end": 49.818, "duration": 285.9, "wordIdx": 40}, {"charIdx": 0, "char": "ل", "start": 49.838, "end": 49.879, "duration": 40.6, "wordIdx": 41}, {"charIdx": 1, "char": "ل", "start": 49.879, "end": 49.96, "duration": 81.3, "wordIdx": 41}, {"charIdx": 2, "char": "ه", "start": 49.96, "end": 50.062, "duration": 101.6, "wordIdx": 41}, {"charIdx": 3, "char": "د", "start": 50.062, "end": 50.224, "duration": 162.6, "wordIdx": 41}, {"charIdx": 4, "char": "ي", "start": 50.224, "end": 50.326, "duration": 101.6, "wordIdx": 41}, {"charIdx": 0, "char": "و", "start": 51.442, "end": 51.625, "duration": 183.3, "wordIdx": 42}, {"charIdx": 1, "char": "إ", "start": 51.625, "end": 52.562, "duration": 936.8, "wordIdx": 42}, {"charIdx": 2, "char": "ن", "start": 52.562, "end": 52.725, "duration": 162.9, "wordIdx": 42}, {"charIdx": 0, "char": "ل", "start": 52.805, "end": 52.888, "duration": 82.6, "wordIdx": 43}, {"charIdx": 1, "char": "ن", "start": 52.888, "end": 52.97, "duration": 82.6, "wordIdx": 43}, {"charIdx": 2, "char": "ا", "start": 52.97, "end": 53.053, "duration": 82.6, "wordIdx": 43}, {"charIdx": 0, "char": "ل", "start": 53.527, "end": 53.75, "duration": 223.4, "wordIdx": 44}, {"charIdx": 1, "char": "ل", "start": 53.75, "end": 53.933, "duration": 182.8, "wordIdx": 44}, {"charIdx": 2, "char": "آ", "start": 53.933, "end": 54.096, "duration": 162.5, "wordIdx": 44}, {"charIdx": 3, "char": "خ", "start": 54.096, "end": 54.36, "duration": 264.1, "wordIdx": 44}, {"charIdx": 4, "char": "ر", "start": 54.36, "end": 54.604, "duration": 243.7, "wordIdx": 44}, {"charIdx": 5, "char": "ة", "start": 54.604, "end": 54.929, "duration": 325.0, "wordIdx": 44}, {"charIdx": 0, "char": "و", "start": 55.171, "end": 55.374, "duration": 202.7, "wordIdx": 45}, {"charIdx": 1, "char": "ا", "start": 55.374, "end": 55.597, "duration": 223.0, "wordIdx": 45}, {"charIdx": 2, "char": "ل", "start": 55.597, "end": 55.82, "duration": 223.0, "wordIdx": 45}, {"charIdx": 3, "char": "أ", "start": 55.82, "end": 56.083, "duration": 263.5, "wordIdx": 45}, {"charIdx": 4, "char": "و", "start": 56.083, "end": 56.225, "duration": 141.9, "wordIdx": 45}, {"charIdx": 5, "char": "ل", "start": 56.225, "end": 56.955, "duration": 729.8, "wordIdx": 45}, {"charIdx": 6, "char": "ي", "start": 56.7, "end": 56.955, "duration": 254.9, "wordIdx": 45}, {"charIdx": 0, "char": "ف", "start": 57.055, "end": 57.175, "duration": 120.3, "wordIdx": 46}, {"charIdx": 1, "char": "أ", "start": 57.175, "end": 57.316, "duration": 140.3, "wordIdx": 46}, {"charIdx": 2, "char": "ن", "start": 57.316, "end": 57.516, "duration": 200.5, "wordIdx": 46}, {"charIdx": 3, "char": "ذ", "start": 57.516, "end": 58.338, "duration": 822.0, "wordIdx": 46}, {"charIdx": 4, "char": "ر", "start": 58.338, "end": 58.519, "duration": 180.4, "wordIdx": 46}, {"charIdx": 5, "char": "ت", "start": 58.519, "end": 58.759, "duration": 240.6, "wordIdx": 46}, {"charIdx": 6, "char": "ك", "start": 58.759, "end": 59.02, "duration": 260.6, "wordIdx": 46}, {"charIdx": 7, "char": "م", "start": 59.02, "end": 59.24, "duration": 220.5, "wordIdx": 46}, {"charIdx": 0, "char": "ن", "start": 59.643, "end": 60.029, "duration": 386.2, "wordIdx": 47}, {"charIdx": 1, "char": "ا", "start": 60.029, "end": 60.171, "duration": 142.3, "wordIdx": 47}, {"charIdx": 2, "char": "ر", "start": 60.171, "end": 60.598, "duration": 426.8, "wordIdx": 47}, {"charIdx": 3, "char": "ا", "start": 60.598, "end": 60.862, "duration": 264.2, "wordIdx": 47}, {"charIdx": 0, "char": "ت", "start": 61.125, "end": 61.166, "duration": 40.7, "wordIdx": 48}, {"charIdx": 1, "char": "ل", "start": 61.166, "end": 61.206, "duration": 40.7, "wordIdx": 48}, {"charIdx": 2, "char": "ظ", "start": 61.206, "end": 61.552, "duration": 345.8, "wordIdx": 48}, {"charIdx": 3, "char": "ي", "start": 61.552, "end": 61.756, "duration": 203.4, "wordIdx": 48}, {"charIdx": 0, "char": "ل", "start": 62.676, "end": 62.821, "duration": 145.3, "wordIdx": 49}, {"charIdx": 1, "char": "ا", "start": 62.821, "end": 63.049, "duration": 228.2, "wordIdx": 49}, {"charIdx": 0, "char": "ي", "start": 63.169, "end": 63.331, "duration": 161.3, "wordIdx": 50}, {"charIdx": 1, "char": "ص", "start": 63.331, "end": 63.593, "duration": 262.1, "wordIdx": 50}, {"charIdx": 2, "char": "ل", "start": 63.593, "end": 63.774, "duration": 181.5, "wordIdx": 50}, {"charIdx": 3, "char": "ي", "start": 63.774, "end": 64.097, "duration": 322.6, "wordIdx": 50}, {"charIdx": 4, "char": "ه", "start": 64.097, "end": 64.258, "duration": 161.3, "wordIdx": 50}, {"charIdx": 5, "char": "ا", "start": 64.258, "end": 64.46, "duration": 201.6, "wordIdx": 50}, {"charIdx": 0, "char": "إ", "start": 66.055, "end": 66.409, "duration": 354.3, "wordIdx": 51}, {"charIdx": 1, "char": "ل", "start": 66.409, "end": 66.45, "duration": 41.7, "wordIdx": 51}, {"charIdx": 2, "char": "ا", "start": 66.45, "end": 66.513, "duration": 62.5, "wordIdx": 51}, {"charIdx": 0, "char": "ا", "start": 66.633, "end": 66.796, "duration": 162.4, "wordIdx": 52}, {"charIdx": 1, "char": "ل", "start": 66.796, "end": 67.019, "duration": 223.3, "wordIdx": 52}, {"charIdx": 2, "char": "أ", "start": 67.019, "end": 67.283, "duration": 263.9, "wordIdx": 52}, {"charIdx": 3, "char": "ش", "start": 67.283, "end": 67.445, "duration": 162.4, "wordIdx": 52}, {"charIdx": 4, "char": "ق", "start": 67.445, "end": 68.115, "duration": 669.8, "wordIdx": 52}, {"charIdx": 5, "char": "ي", "start": 67.865, "end": 68.115, "duration": 250.3, "wordIdx": 52}, {"charIdx": 0, "char": "ا", "start": 68.598, "end": 68.847, "duration": 249.6, "wordIdx": 53}, {"charIdx": 1, "char": "ل", "start": 68.847, "end": 68.972, "duration": 124.8, "wordIdx": 53}, {"charIdx": 2, "char": "ذ", "start": 68.972, "end": 69.076, "duration": 104.0, "wordIdx": 53}, {"charIdx": 3, "char": "ي", "start": 68.946, "end": 69.076, "duration": 130.0, "wordIdx": 53}, {"charIdx": 0, "char": "ك", "start": 69.277, "end": 69.339, "duration": 61.6, "wordIdx": 54}, {"charIdx": 1, "char": "ذ", "start": 69.339, "end": 69.421, "duration": 82.2, "wordIdx": 54}, {"charIdx": 2, "char": "ب", "start": 69.421, "end": 69.667, "duration": 246.5, "wordIdx": 54}, {"charIdx": 0, "char": "و", "start": 70.158, "end": 70.259, "duration": 101.1, "wordIdx": 55}, {"charIdx": 1, "char": "ت", "start": 70.259, "end": 70.401, "duration": 141.6, "wordIdx": 55}, {"charIdx": 2, "char": "و", "start": 70.401, "end": 70.643, "duration": 242.7, "wordIdx": 55}, {"charIdx": 3, "char": "ل", "start": 70.643, "end": 70.745, "duration": 101.1, "wordIdx": 55}, {"charIdx": 4, "char": "ي", "start": 70.745, "end": 70.866, "duration": 121.3, "wordIdx": 55}, {"charIdx": 0, "char": "و", "start": 72.24, "end": 72.321, "duration": 80.9, "wordIdx": 56}, {"charIdx": 1, "char": "س", "start": 72.321, "end": 72.361, "duration": 40.4, "wordIdx": 56}, {"charIdx": 2, "char": "ي", "start": 72.361, "end": 72.422, "duration": 60.6, "wordIdx": 56}, {"charIdx": 3, "char": "ج", "start": 72.422, "end": 72.604, "duration": 181.9, "wordIdx": 56}, {"charIdx": 4, "char": "ن", "start": 72.604, "end": 72.725, "duration": 121.3, "wordIdx": 56}, {"charIdx": 5, "char": "ب", "start": 72.725, "end": 72.867, "duration": 141.5, "wordIdx": 56}, {"charIdx": 6, "char": "ه", "start": 72.867, "end": 72.968, "duration": 101.1, "wordIdx": 56}, {"charIdx": 7, "char": "ا", "start": 72.968, "end": 73.069, "duration": 101.1, "wordIdx": 56}, {"charIdx": 0, "char": "ا", "start": 74.93, "end": 74.991, "duration": 60.9, "wordIdx": 57}, {"charIdx": 1, "char": "ل", "start": 74.991, "end": 75.072, "duration": 81.2, "wordIdx": 57}, {"charIdx": 2, "char": "أ", "start": 75.072, "end": 75.316, "duration": 243.6, "wordIdx": 57}, {"charIdx": 3, "char": "ت", "start": 75.316, "end": 75.417, "duration": 101.5, "wordIdx": 57}, {"charIdx": 4, "char": "ق", "start": 75.417, "end": 75.519, "duration": 101.5, "wordIdx": 57}, {"charIdx": 5, "char": "ى", "start": 75.519, "end": 75.681, "duration": 162.4, "wordIdx": 57}, {"wordIdx": 58, "charIdx": 0, "char": "ا", "start": 75.945, "end": 75.965, "duration": 20.0}, {"wordIdx": 58, "charIdx": 1, "char": "ل", "start": 75.965, "end": 75.985, "duration": 20.0}, {"wordIdx": 58, "charIdx": 2, "char": "ذ", "start": 75.985, "end": 76.005, "duration": 20.0}, {"wordIdx": 58, "charIdx": 3, "char": "ي", "start": 76.005, "end": 76.025, "duration": 20.0}, {"charIdx": 0, "char": "ي", "start": 76.086, "end": 76.496, "duration": 410.0, "wordIdx": 59}, {"charIdx": 1, "char": "ؤ", "start": 76.496, "end": 76.66, "duration": 164.0, "wordIdx": 59}, {"charIdx": 2, "char": "ت", "start": 76.66, "end": 76.906, "duration": 246.0, "wordIdx": 59}, {"charIdx": 3, "char": "ي", "start": 76.691, "end": 76.906, "duration": 215.2, "wordIdx": 59}, {"charIdx": 0, "char": "م", "start": 77.027, "end": 77.092, "duration": 64.2, "wordIdx": 60}, {"charIdx": 1, "char": "ا", "start": 77.092, "end": 77.327, "duration": 235.4, "wordIdx": 60}, {"charIdx": 0, "char": "ل", "start": 77.55, "end": 77.695, "duration": 144.5, "wordIdx": 61}, {"charIdx": 1, "char": "ه", "start": 77.695, "end": 77.963, "duration": 268.3, "wordIdx": 61}, {"charIdx": 0, "char": "ي", "start": 78.268, "end": 78.471, "duration": 202.5, "wordIdx": 62}, {"charIdx": 1, "char": "ت", "start": 78.471, "end": 78.572, "duration": 101.2, "wordIdx": 62}, {"charIdx": 2, "char": "ز", "start": 78.572, "end": 78.714, "duration": 141.7, "wordIdx": 62}, {"charIdx": 3, "char": "ك", "start": 78.714, "end": 79.159, "duration": 445.4, "wordIdx": 62}, {"charIdx": 4, "char": "ي", "start": 79.159, "end": 79.341, "duration": 182.2, "wordIdx": 62}, {"charIdx": 0, "char": "و", "start": 80.15, "end": 80.316, "duration": 166.5, "wordIdx": 63}, {"charIdx": 1, "char": "م", "start": 80.316, "end": 80.462, "duration": 145.7, "wordIdx": 63}, {"charIdx": 2, "char": "ا", "start": 80.462, "end": 80.691, "duration": 228.9, "wordIdx": 63}, {"charIdx": 0, "char": "ل", "start": 80.791, "end": 80.893, "duration": 102.0, "wordIdx": 64}, {"charIdx": 1, "char": "أ", "start": 80.893, "end": 80.913, "duration": 20.4, "wordIdx": 64}, {"charIdx": 2, "char": "ح", "start": 80.913, "end": 80.995, "duration": 81.6, "wordIdx": 64}, {"charIdx": 3, "char": "د", "start": 80.995, "end": 81.179, "duration": 183.6, "wordIdx": 64}, {"charIdx": 0, "char": "ع", "start": 81.933, "end": 82.096, "duration": 162.7, "wordIdx": 65}, {"charIdx": 1, "char": "ن", "start": 82.096, "end": 82.604, "duration": 508.3, "wordIdx": 65}, {"charIdx": 2, "char": "د", "start": 82.604, "end": 82.706, "duration": 101.7, "wordIdx": 65}, {"charIdx": 3, "char": "ه", "start": 82.706, "end": 82.767, "duration": 61.0, "wordIdx": 65}, {"charIdx": 0, "char": "م", "start": 83.479, "end": 83.955, "duration": 475.6, "wordIdx": 66}, {"charIdx": 1, "char": "ن", "start": 83.634, "end": 83.955, "duration": 320.5, "wordIdx": 66}, {"charIdx": 0, "char": "ن", "start": 84.217, "end": 84.399, "duration": 182.4, "wordIdx": 67}, {"charIdx": 1, "char": "ع", "start": 84.399, "end": 84.744, "duration": 344.6, "wordIdx": 67}, {"charIdx": 2, "char": "م", "start": 84.744, "end": 84.906, "duration": 162.2, "wordIdx": 67}, {"charIdx": 3, "char": "ة", "start": 84.906, "end": 85.717, "duration": 810.9, "wordIdx": 67}, {"charIdx": 0, "char": "ت", "start": 85.757, "end": 85.919, "duration": 161.8, "wordIdx": 68}, {"charIdx": 1, "char": "ج", "start": 85.919, "end": 86.242, "duration": 323.5, "wordIdx": 68}, {"charIdx": 2, "char": "ز", "start": 86.242, "end": 86.445, "duration": 202.2, "wordIdx": 68}, {"charIdx": 3, "char": "ي", "start": 86.445, "end": 87.86, "duration": 1415.3, "wordIdx": 68}, {"charIdx": 0, "char": "إ", "start": 87.921, "end": 88.004, "duration": 82.9, "wordIdx": 69}, {"charIdx": 1, "char": "ل", "start": 88.004, "end": 88.129, "duration": 124.3, "wordIdx": 69}, {"charIdx": 2, "char": "ا", "start": 88.129, "end": 88.274, "duration": 145.1, "wordIdx": 69}, {"charIdx": 0, "char": "ا", "start": 88.542, "end": 88.766, "duration": 224.6, "wordIdx": 70}, {"charIdx": 1, "char": "ب", "start": 88.766, "end": 88.909, "duration": 142.9, "wordIdx": 70}, {"charIdx": 2, "char": "ت", "start": 88.909, "end": 89.093, "duration": 183.8, "wordIdx": 70}, {"charIdx": 3, "char": "غ", "start": 89.093, "end": 89.216, "duration": 122.5, "wordIdx": 70}, {"charIdx": 4, "char": "ا", "start": 89.216, "end": 89.318, "duration": 102.1, "wordIdx": 70}, {"charIdx": 5, "char": "ء", "start": 89.318, "end": 89.44, "duration": 122.5, "wordIdx": 70}, {"charIdx": 0, "char": "و", "start": 89.522, "end": 89.704, "duration": 181.7, "wordIdx": 71}, {"charIdx": 1, "char": "ج", "start": 89.704, "end": 90.491, "duration": 787.4, "wordIdx": 71}, {"charIdx": 2, "char": "ه", "start": 90.491, "end": 90.693, "duration": 201.9, "wordIdx": 71}, {"charIdx": 0, "char": "ر", "start": 91.521, "end": 91.642, "duration": 121.1, "wordIdx": 72}, {"charIdx": 1, "char": "ب", "start": 91.642, "end": 91.924, "duration": 282.5, "wordIdx": 72}, {"charIdx": 2, "char": "ه", "start": 91.924, "end": 92.025, "duration": 100.9, "wordIdx": 72}, {"charIdx": 0, "char": "ا", "start": 92.53, "end": 92.571, "duration": 40.4, "wordIdx": 73}, {"charIdx": 1, "char": "ل", "start": 92.571, "end": 92.712, "duration": 141.3, "wordIdx": 73}, {"charIdx": 2, "char": "أ", "start": 92.712, "end": 92.914, "duration": 201.8, "wordIdx": 73}, {"charIdx": 3, "char": "ع", "start": 92.914, "end": 93.055, "duration": 141.3, "wordIdx": 73}, {"charIdx": 4, "char": "ل", "start": 93.055, "end": 93.237, "duration": 181.7, "wordIdx": 73}, {"charIdx": 5, "char": "ي", "start": 93.237, "end": 93.378, "duration": 141.3, "wordIdx": 73}, {"charIdx": 0, "char": "و", "start": 94.507, "end": 94.608, "duration": 100.9, "wordIdx": 74}, {"charIdx": 1, "char": "ل", "start": 94.608, "end": 94.709, "duration": 100.9, "wordIdx": 74}, {"charIdx": 2, "char": "س", "start": 94.709, "end": 94.931, "duration": 222.1, "wordIdx": 74}, {"charIdx": 3, "char": "و", "start": 94.931, "end": 95.052, "duration": 121.1, "wordIdx": 74}, {"charIdx": 4, "char": "ف", "start": 95.052, "end": 95.234, "duration": 181.7, "wordIdx": 74}, {"charIdx": 0, "char": "ي", "start": 95.931, "end": 96.301, "duration": 369.6, "wordIdx": 75}, {"charIdx": 1, "char": "ر", "start": 96.301, "end": 96.453, "duration": 152.2, "wordIdx": 75}, {"charIdx": 2, "char": "ض", "start": 96.453, "end": 96.627, "duration": 173.9, "wordIdx": 75}, {"charIdx": 3, "char": "ي", "start": 96.415, "end": 96.627, "duration": 212.0, "wordIdx": 75}]