[
  {
    "word": "وهنا",
    "start": 0,
    "end": 980
  },
  {
    "word": "نحن",
    "start": 980,
    "end": 1280
  },
  {
    "word": "إخوة",
    "start": 1280,
    "end": 2020
  },
  {
    "word": "الإيمان",
    "start": 2020,
    "end": 2420
  },
  {
    "word": "والإسلام",
    "start": 2420,
    "end": 2980
  },
  {
    "word": "نستكمل",
    "start": 2980,
    "end": 4040
  },
  {
    "word": "صلاة",
    "start": 4040,
    "end": 4660
  },
  {
    "word": "القيام",
    "start": 4660,
    "end": 5220
  },
  {
    "word": "يؤمن",
    "start": 5220,
    "end": 5840
  },
  {
    "word": "في",
    "start": 5840,
    "end": 6180
  },
  {
    "word": "الستر",
    "start": 6180,
    "end": 6640
  },
  {
    "word": "كعاتي",
    "start": 6640,
    "end": 7160
  },
  {
    "word": "التالية",
    "start": 7160,
    "end": 7660
  },
  {
    "word": "فضيلة",
    "start": 7660,
    "end": 8580
  },
  {
    "word": "الشيخ",
    "start": 8580,
    "end": 9120
  },
  {
    "word": "محمد",
    "start": 9120,
    "end": 9820
  },
  {
    "word": "أحمد",
    "start": 9820,
    "end": 10160
  },
  {
    "word": "حزن",
    "start": 10160,
    "end": 10460
  },
  {
    "word": "ستقيم",
    "start": 48160,
    "end": 49340
  },
  {
    "word": "وستو",
    "start": 49340,
    "end": 49920
  },
  {
    "word": "تراص",
    "start": 49920,
    "end": 50420
  },
  {
    "word": "وعتدل",
    "start": 50420,
    "end": 51020
  },
  {
    "word": "صلاة",
    "start": 54120,
    "end": 55120
  },
  {
    "word": "إن",
    "start": 55120,
    "end": 55320
  },
  {
    "word": "شاء",
    "start": 55320,
    "end": 55500
  },
  {
    "word": "الله",
    "start": 55500,
    "end": 55740
  },
  {
    "word": "برواية",
    "start": 55740,
    "end": 56500
  },
  {
    "word": "قنبل",
    "start": 56500,
    "end": 57320
  },
  {
    "word": "عن",
    "start": 57320,
    "end": 57820
  },
  {
    "word": "ابني",
    "start": 57820,
    "end": 58040
  },
  {
    "word": "كثير",
    "start": 58040,
    "end": 58600
  },
  {
    "word": "رضي",
    "start": 58600,
    "end": 59080
  },
  {
    "word": "الله",
    "start": 59080,
    "end": 59340
  },
  {
    "word": "تعالى",
    "start": 59340,
    "end": 59960
  },
  {
    "word": "عنهما",
    "start": 59960,
    "end": 60460
  },
  {
    "word": "الله",
    "start": 66439,
    "end": 67839
  },
  {
    "word": "أكبر",
    "start": 67839,
    "end": 69240
  },
  {
    "word": "بسم",
    "start": 76500,
    "end": 77900
  },
  {
    "word": "الله",
    "start": 77900,
    "end": 78260
  },
  {
    "word": "الرحمن",
    "start": 78260,
    "end": 78940
  },
  {
    "word": "الرحيم",
    "start": 78940,
    "end": 80160
  },
  {
    "word": "الحمد",
    "start": 80160,
    "end": 81860
  },
  {
    "word": "لله",
    "start": 81860,
    "end": 82460
  },
  {
    "word": "رب",
    "start": 82460,
    "end": 82880
  },
  {
    "word": "العالمين",
    "start": 82880,
    "end": 84560
  },
  {
    "word": "الرحمن",
    "start": 84560,
    "end": 86100
  },
  {
    "word": "الرحيم",
    "start": 86100,
    "end": 87620
  },
  {
    "word": "ملك",
    "start": 87620,
    "end": 89060
  },
  {
    "word": "يوم",
    "start": 89060,
    "end": 89660
  },
  {
    "word": "الدين",
    "start": 89660,
    "end": 91320
  },
  {
    "word": "إياك",
    "start": 91320,
    "end": 93260
  },
  {
    "word": "نعبد",
    "start": 93260,
    "end": 93760
  },
  {
    "word": "وإياك",
    "start": 93760,
    "end": 94880
  },
  {
    "word": "نستعين",
    "start": 94880,
    "end": 96300
  },
  {
    "word": "إهدنا",
    "start": 96300,
    "end": 98100
  },
  {
    "word": "السراط",
    "start": 98100,
    "end": 98980
  },
  {
    "word": "المستقيم",
    "start": 98980,
    "end": 101080
  },
  {
    "word": "سراط",
    "start": 102080,
    "end": 102980
  },
  {
    "word": "الذين",
    "start": 102980,
    "end": 103920
  },
  {
    "word": "أن",
    "start": 103920,
    "end": 104300
  },
  {
    "word": "عمت",
    "start": 104300,
    "end": 104960
  },
  {
    "word": "عليهم",
    "start": 104960,
    "end": 106000
  },
  {
    "word": "وقير",
    "start": 106000,
    "end": 106780
  },
  {
    "word": "المغضوب",
    "start": 106780,
    "end": 108060
  },
  {
    "word": "عليهم",
    "start": 108060,
    "end": 109340
  },
  {
    "word": "وللضالين",
    "start": 109340,
    "end": 115960
  },
  {
    "word": "أمين",
    "start": 118119,
    "end": 119520
  },
  {
    "word": "وجاوزنا",
    "start": 122759,
    "end": 124160
  },
  {
    "word": "ببني",
    "start": 124160,
    "end": 124960
  },
  {
    "word": "إسرائيل",
    "start": 124960,
    "end": 127620
  },
  {
    "word": "البحر",
    "start": 127620,
    "end": 128419
  },
  {
    "word": "فأتوا",
    "start": 128419,
    "end": 129300
  },
  {
    "word": "على",
    "start": 129300,
    "end": 129680
  },
  {
    "word": "قوم",
    "start": 129680,
    "end": 130479
  },
  {
    "word": "يعكفون",
    "start": 130479,
    "end": 132620
  },
  {
    "word": "على",
    "start": 132620,
    "end": 133140
  },
  {
    "word": "أصنام",
    "start": 133140,
    "end": 134540
  },
  {
    "word": "له",
    "start": 134540,
    "end": 135100
  },
  {
    "word": "قالوا",
    "start": 136600,
    "end": 138000
  },
  {
    "word": "يا",
    "start": 138000,
    "end": 138340
  },
  {
    "word": "موسى",
    "start": 138340,
    "end": 139240
  },
  {
    "word": "جعلنا",
    "start": 139240,
    "end": 140420
  },
  {
    "word": "إله",
    "start": 140420,
    "end": 141320
  },
  {
    "word": "كما",
    "start": 141320,
    "end": 142800
  },
  {
    "word": "لهم",
    "start": 142800,
    "end": 143520
  },
  {
    "word": "آله",
    "start": 143520,
    "end": 144660
  },
  {
    "word": "قال",
    "start": 144660,
    "end": 146400
  },
  {
    "word": "إنكم",
    "start": 146400,
    "end": 148060
  },
  {
    "word": "قوم",
    "start": 148060,
    "end": 149120
  },
  {
    "word": "تجهلون",
    "start": 149120,
    "end": 151560
  },
  {
    "word": "إن",
    "start": 152560,
    "end": 153580
  },
  {
    "word": "هؤلاء",
    "start": 153580,
    "end": 156780
  },
  {
    "word": "متبروا",
    "start": 156780,
    "end": 158000
  },
  {
    "word": "ما",
    "start": 158000,
    "end": 159020
  },
  {
    "word": "هموا",
    "start": 159020,
    "end": 159940
  },
  {
    "word": "فيه",
    "start": 159940,
    "end": 166600
  },
  {
    "word": "وباطلوا",
    "start": 166600,
    "end": 168140
  },
  {
    "word": "ما",
    "start": 168140,
    "end": 168980
  },
  {
    "word": "كانوا",
    "start": 168980,
    "end": 170280
  },
  {
    "word": "يعملون",
    "start": 170280,
    "end": 172080
  },
  {
    "word": "قال",
    "start": 173080,
    "end": 174020
  },
  {
    "word": "أغير",
    "start": 174020,
    "end": 174940
  },
  {
    "word": "الله",
    "start": 174940,
    "end": 175700
  },
  {
    "word": "أبغيكم",
    "start": 175700,
    "end": 177380
  },
  {
    "word": "إلها",
    "start": 177380,
    "end": 186040
  },
  {
    "word": "وهو",
    "start": 186040,
    "end": 187180
  },
  {
    "word": "فضلكم",
    "start": 187180,
    "end": 188520
  },
  {
    "word": "على",
    "start": 188520,
    "end": 189400
  },
  {
    "word": "العالمين",
    "start": 189400,
    "end": 192060
  },
  {
    "word": "وإذ",
    "start": 193060,
    "end": 194080
  },
  {
    "word": "أن",
    "start": 194080,
    "end": 194520
  },
  {
    "word": "جيناكم",
    "start": 194520,
    "end": 196120
  },
  {
    "word": "من",
    "start": 196120,
    "end": 196880
  },
  {
    "word": "آله",
    "start": 196880,
    "end": 197580
  },
  {
    "word": "فضعون",
    "start": 197580,
    "end": 198640
  },
  {
    "word": "يسومونكم",
    "start": 198640,
    "end": 200420
  },
  {
    "word": "سوء",
    "start": 200420,
    "end": 202420
  },
  {
    "word": "العذاب",
    "start": 202420,
    "end": 203119
  },
  {
    "word": "يسومونكم",
    "start": 206899,
    "end": 208299
  },
  {
    "word": "سوء",
    "start": 208299,
    "end": 209700
  },
  {
    "word": "العذاب",
    "start": 209700,
    "end": 210399
  },
  {
    "word": "يقتلون",
    "start": 210820,
    "end": 212340
  },
  {
    "word": "أبناءكم",
    "start": 212340,
    "end": 215020
  },
  {
    "word": "ويستحيون",
    "start": 215020,
    "end": 217220
  },
  {
    "word": "نساءكم",
    "start": 217220,
    "end": 220140
  },
  {
    "word": "وفي",
    "start": 220140,
    "end": 221880
  },
  {
    "word": "ذلكموا",
    "start": 221880,
    "end": 223640
  },
  {
    "word": "بلاء",
    "start": 223640,
    "end": 226920
  },
  {
    "word": "من",
    "start": 226920,
    "end": 227880
  },
  {
    "word": "ربكم",
    "start": 227880,
    "end": 229240
  },
  {
    "word": "عظيم",
    "start": 229240,
    "end": 231420
  },
  {
    "word": "ووعدنا",
    "start": 231420,
    "end": 233000
  },
  {
    "word": "موسى",
    "start": 233000,
    "end": 234060
  },
  {
    "word": "فلا",
    "start": 234060,
    "end": 234760
  },
  {
    "word": "فين",
    "start": 234760,
    "end": 235500
  },
  {
    "word": "ليلة",
    "start": 235500,
    "end": 236460
  },
  {
    "word": "وأتمنىها",
    "start": 236460,
    "end": 239140
  },
  {
    "word": "بعشر",
    "start": 239140,
    "end": 240120
  },
  {
    "word": "فتمميقات",
    "start": 240120,
    "end": 243780
  },
  {
    "word": "ربه",
    "start": 243780,
    "end": 245060
  },
  {
    "word": "أربعين",
    "start": 245060,
    "end": 246780
  },
  {
    "word": "ليلة",
    "start": 246780,
    "end": 247740
  },
  {
    "word": "وقال",
    "start": 248740,
    "end": 250320
  },
  {
    "word": "موسى",
    "start": 250320,
    "end": 251400
  },
  {
    "word": "لأخيه",
    "start": 251400,
    "end": 252740
  },
  {
    "word": "هارون",
    "start": 252740,
    "end": 254360
  },
  {
    "word": "خلفني",
    "start": 254360,
    "end": 255460
  },
  {
    "word": "في",
    "start": 255460,
    "end": 255940
  },
  {
    "word": "قومي",
    "start": 255940,
    "end": 257220
  },
  {
    "word": "وأصلح",
    "start": 257220,
    "end": 260600
  },
  {
    "word": "ولا",
    "start": 260600,
    "end": 261019
  },
  {
    "word": "تتبع",
    "start": 261019,
    "end": 262360
  },
  {
    "word": "سبيل",
    "start": 262360,
    "end": 263420
  },
  {
    "word": "المفسدين",
    "start": 263420,
    "end": 265360
  },
  {
    "word": "ولما",
    "start": 266360,
    "end": 267760
  },
  {
    "word": "جاء",
    "start": 267760,
    "end": 269960
  },
  {
    "word": "موسى",
    "start": 269960,
    "end": 271480
  },
  {
    "word": "لميقاتنا",
    "start": 271480,
    "end": 273340
  },
  {
    "word": "وكلمه",
    "start": 273340,
    "end": 275040
  },
  {
    "word": "ربه",
    "start": 275040,
    "end": 280020
  },
  {
    "word": "قال",
    "start": 280020,
    "end": 280780
  },
  {
    "word": "رب",
    "start": 280780,
    "end": 281680
  },
  {
    "word": "أرني",
    "start": 281680,
    "end": 282820
  },
  {
    "word": "أنظر",
    "start": 282820,
    "end": 284920
  },
  {
    "word": "إليك",
    "start": 284920,
    "end": 286440
  },
  {
    "word": "قال",
    "start": 287180,
    "end": 287880
  },
  {
    "word": "لان",
    "start": 287880,
    "end": 288820
  },
  {
    "word": "تراني",
    "start": 288820,
    "end": 290340
  },
  {
    "word": "ولكنوظر",
    "start": 290340,
    "end": 292860
  },
  {
    "word": "إلى",
    "start": 292860,
    "end": 293200
  },
  {
    "word": "الجبل",
    "start": 293200,
    "end": 294060
  },
  {
    "word": "فإن",
    "start": 294060,
    "end": 294940
  },
  {
    "word": "استقرم",
    "start": 294940,
    "end": 296300
  },
  {
    "word": "كانه",
    "start": 296300,
    "end": 297620
  },
  {
    "word": "فسوف",
    "start": 297620,
    "end": 298460
  },
  {
    "word": "تراني",
    "start": 298460,
    "end": 300320
  },
  {
    "word": "فلما",
    "start": 301320,
    "end": 303060
  },
  {
    "word": "تجل",
    "start": 303060,
    "end": 304020
  },
  {
    "word": "ربه",
    "start": 304020,
    "end": 305320
  },
  {
    "word": "للجبل",
    "start": 305320,
    "end": 306440
  },
  {
    "word": "جعله",
    "start": 306440,
    "end": 307600
  },
  {
    "word": "دك",
    "start": 307600,
    "end": 308320
  },
  {
    "word": "وخذ",
    "start": 308320,
    "end": 309960
  },
  {
    "word": "موسى",
    "start": 309960,
    "end": 311280
  },
  {
    "word": "صعقا",
    "start": 311280,
    "end": 312920
  },
  {
    "word": "فلما",
    "start": 312920,
    "end": 314760
  },
  {
    "word": "أفاق",
    "start": 314760,
    "end": 315960
  },
  {
    "word": "قال",
    "start": 315960,
    "end": 316640
  },
  {
    "word": "سبحانك",
    "start": 316640,
    "end": 319500
  },
  {
    "word": "تبت",
    "start": 319500,
    "end": 322380
  },
  {
    "word": "إليك",
    "start": 322380,
    "end": 323340
  },
  {
    "word": "وأنا",
    "start": 323340,
    "end": 324080
  },
  {
    "word": "أول",
    "start": 324080,
    "end": 324800
  },
  {
    "word": "المؤمنين",
    "start": 324800,
    "end": 326960
  },
  {
    "word": "قال",
    "start": 327960,
    "end": 328880
  },
  {
    "word": "يا",
    "start": 328880,
    "end": 329600
  },
  {
    "word": "موسى",
    "start": 329600,
    "end": 330820
  },
  {
    "word": "إني",
    "start": 330820,
    "end": 331900
  },
  {
    "word": "أصطفيتك",
    "start": 331900,
    "end": 333520
  },
  {
    "word": "على",
    "start": 333520,
    "end": 334040
  },
  {
    "word": "الناس",
    "start": 334040,
    "end": 335700
  },
  {
    "word": "برسالتي",
    "start": 335700,
    "end": 337460
  },
  {
    "word": "وبكلامي",
    "start": 337460,
    "end": 340480
  },
  {
    "word": "قال",
    "start": 340480,
    "end": 341140
  },
  {
    "word": "يا",
    "start": 341140,
    "end": 341880
  },
  {
    "word": "موسى",
    "start": 341880,
    "end": 343160
  },
  {
    "word": "إني",
    "start": 343160,
    "end": 344280
  },
  {
    "word": "أصطفيتك",
    "start": 344280,
    "end": 345960
  },
  {
    "word": "على",
    "start": 345960,
    "end": 346460
  },
  {
    "word": "الناس",
    "start": 346460,
    "end": 348160
  },
  {
    "word": "برسالتي",
    "start": 348160,
    "end": 349940
  },
  {
    "word": "وبكلامي",
    "start": 349940,
    "end": 351880
  },
  {
    "word": "فخذ",
    "start": 351880,
    "end": 352640
  },
  {
    "word": "ما",
    "start": 352640,
    "end": 353180
  },
  {
    "word": "آتيتك",
    "start": 353180,
    "end": 358580
  },
  {
    "word": "وكم",
    "start": 358580,
    "end": 359440
  },
  {
    "word": "من",
    "start": 359440,
    "end": 360880
  },
  {
    "word": "الشاك",
    "start": 360880,
    "end": 362180
  },
  {
    "word": "وكتبنا",
    "start": 363180,
    "end": 364640
  },
  {
    "word": "له",
    "start": 364640,
    "end": 365020
  },
  {
    "word": "في",
    "start": 365020,
    "end": 365480
  },
  {
    "word": "الألواح",
    "start": 365480,
    "end": 366600
  },
  {
    "word": "من",
    "start": 366600,
    "end": 367200
  },
  {
    "word": "كل",
    "start": 367200,
    "end": 368320
  },
  {
    "word": "شيء",
    "start": 368320,
    "end": 370120
  },
  {
    "word": "موعظة",
    "start": 370120,
    "end": 371360
  },
  {
    "word": "وتفسيل",
    "start": 371360,
    "end": 373200
  },
  {
    "word": "لكل",
    "start": 373200,
    "end": 374040
  },
  {
    "word": "شيء",
    "start": 374040,
    "end": 376100
  },
  {
    "word": "فخذها",
    "start": 376100,
    "end": 377340
  },
  {
    "word": "بقوة",
    "start": 377340,
    "end": 382180
  },
  {
    "word": "وأمر",
    "start": 382180,
    "end": 383920
  },
  {
    "word": "قومك",
    "start": 383920,
    "end": 384960
  },
  {
    "word": "يأخذوا",
    "start": 384960,
    "end": 386140
  },
  {
    "word": "بأحسنها",
    "start": 386140,
    "end": 387640
  },
  {
    "word": "سأريكم",
    "start": 389100,
    "end": 390500
  },
  {
    "word": "دار",
    "start": 390500,
    "end": 391680
  },
  {
    "word": "الفاسقين",
    "start": 391680,
    "end": 393980
  },
  {
    "word": "سأصرف",
    "start": 394640,
    "end": 396320
  },
  {
    "word": "عن",
    "start": 396320,
    "end": 396800
  },
  {
    "word": "آياتي",
    "start": 396800,
    "end": 398060
  },
  {
    "word": "الذين",
    "start": 398060,
    "end": 399020
  },
  {
    "word": "يتكبرون",
    "start": 399020,
    "end": 400620
  },
  {
    "word": "في",
    "start": 400620,
    "end": 400980
  },
  {
    "word": "الأرض",
    "start": 400980,
    "end": 401700
  },
  {
    "word": "بغير",
    "start": 401700,
    "end": 402540
  },
  {
    "word": "الحق",
    "start": 402540,
    "end": 403580
  },
  {
    "word": "وإن",
    "start": 403580,
    "end": 406100
  },
  {
    "word": "يروا",
    "start": 406100,
    "end": 406600
  },
  {
    "word": "كل",
    "start": 406600,
    "end": 407120
  },
  {
    "word": "آية",
    "start": 407120,
    "end": 408040
  },
  {
    "word": "لا",
    "start": 408040,
    "end": 408820
  },
  {
    "word": "يؤمنوا",
    "start": 408820,
    "end": 410060
  },
  {
    "word": "بها",
    "start": 410060,
    "end": 410960
  },
  {
    "word": "وإن",
    "start": 410960,
    "end": 413620
  },
  {
    "word": "يروا",
    "start": 413620,
    "end": 414100
  },
  {
    "word": "سبيل",
    "start": 414100,
    "end": 415040
  },
  {
    "word": "بغشد",
    "start": 415040,
    "end": 415760
  },
  {
    "word": "لا",
    "start": 415760,
    "end": 416220
  },
  {
    "word": "يتخذواه",
    "start": 416220,
    "end": 417960
  },
  {
    "word": "سبيل",
    "start": 417960,
    "end": 419140
  },
  {
    "word": "وإن",
    "start": 419140,
    "end": 421140
  },
  {
    "word": "يروا",
    "start": 421140,
    "end": 421720
  },
  {
    "word": "سبيل",
    "start": 421720,
    "end": 422680
  },
  {
    "word": "الغي",
    "start": 422680,
    "end": 423480
  },
  {
    "word": "يتخذواه",
    "start": 423480,
    "end": 425400
  },
  {
    "word": "سبيل",
    "start": 425400,
    "end": 426800
  },
  {
    "word": "ذلك",
    "start": 427800,
    "end": 429580
  },
  {
    "word": "بأنهموا",
    "start": 429580,
    "end": 431740
  },
  {
    "word": "كذبوا",
    "start": 431740,
    "end": 432960
  },
  {
    "word": "بآياتنا",
    "start": 432960,
    "end": 434860
  },
  {
    "word": "وكانوا",
    "start": 434860,
    "end": 436240
  },
  {
    "word": "عنها",
    "start": 436240,
    "end": 437180
  },
  {
    "word": "غافرين",
    "start": 437180,
    "end": 439260
  },
  {
    "word": "والذين",
    "start": 440260,
    "end": 441820
  },
  {
    "word": "كذبوا",
    "start": 441820,
    "end": 442820
  },
  {
    "word": "بآياتنا",
    "start": 442820,
    "end": 444460
  },
  {
    "word": "ولقاء",
    "start": 444460,
    "end": 447240
  },
  {
    "word": "الآخرة",
    "start": 447240,
    "end": 448440
  },
  {
    "word": "حبطت",
    "start": 448440,
    "end": 449660
  },
  {
    "word": "أعمالهم",
    "start": 449660,
    "end": 451380
  },
  {
    "word": "هل",
    "start": 451380,
    "end": 453260
  },
  {
    "word": "يجزون",
    "start": 453260,
    "end": 454380
  },
  {
    "word": "إلا",
    "start": 454380,
    "end": 455440
  },
  {
    "word": "ما",
    "start": 455440,
    "end": 455980
  },
  {
    "word": "كانوا",
    "start": 455980,
    "end": 457500
  },
  {
    "word": "يعملون",
    "start": 457500,
    "end": 460020
  },
  {
    "word": "والتخذ",
    "start": 461020,
    "end": 462060
  },
  {
    "word": "قوم",
    "start": 462060,
    "end": 462660
  },
  {
    "word": "موسى",
    "start": 462660,
    "end": 463760
  },
  {
    "word": "من",
    "start": 463760,
    "end": 464220
  },
  {
    "word": "بعده",
    "start": 464220,
    "end": 465600
  },
  {
    "word": "من",
    "start": 465600,
    "end": 466080
  },
  {
    "word": "حليه",
    "start": 466080,
    "end": 467300
  },
  {
    "word": "موعجلا",
    "start": 467300,
    "end": 468700
  },
  {
    "word": "جسدا",
    "start": 468700,
    "end": 470060
  },
  {
    "word": "له",
    "start": 470060,
    "end": 470660
  },
  {
    "word": "خوار",
    "start": 470660,
    "end": 472260
  },
  {
    "word": "ألم",
    "start": 474020,
    "end": 474720
  },
  {
    "word": "يروا",
    "start": 474720,
    "end": 475280
  },
  {
    "word": "أنه",
    "start": 475280,
    "end": 476620
  },
  {
    "word": "لا",
    "start": 476620,
    "end": 477280
  },
  {
    "word": "يكلمهم",
    "start": 477280,
    "end": 478760
  },
  {
    "word": "ولا",
    "start": 478760,
    "end": 479600
  },
  {
    "word": "يهديهم",
    "start": 479600,
    "end": 481400
  },
  {
    "word": "سبيل",
    "start": 481400,
    "end": 482860
  },
  {
    "word": "إتخذواه",
    "start": 485080,
    "end": 486480
  },
  {
    "word": "وكانوا",
    "start": 486480,
    "end": 487880
  },
  {
    "word": "ظالمين",
    "start": 487880,
    "end": 489920
  },
  {
    "word": "ولما",
    "start": 490920,
    "end": 492320
  },
  {
    "word": "سقط",
    "start": 492320,
    "end": 493480
  },
  {
    "word": "في",
    "start": 493480,
    "end": 494160
  },
  {
    "word": "أيديهم",
    "start": 494160,
    "end": 495480
  },
  {
    "word": "ورأوا",
    "start": 495480,
    "end": 496680
  },
  {
    "word": "أنهم",
    "start": 496680,
    "end": 498040
  },
  {
    "word": "قد",
    "start": 498040,
    "end": 498900
  },
  {
    "word": "طلوا",
    "start": 498900,
    "end": 500080
  },
  {
    "word": "قالوا",
    "start": 500080,
    "end": 503780
  },
  {
    "word": "لإن",
    "start": 503780,
    "end": 504460
  },
  {
    "word": "لم",
    "start": 504460,
    "end": 504660
  },
  {
    "word": "يرحمنا",
    "start": 504660,
    "end": 506060
  },
  {
    "word": "ربنا",
    "start": 506060,
    "end": 507160
  },
  {
    "word": "ويغفذ",
    "start": 507160,
    "end": 508320
  },
  {
    "word": "لنا",
    "start": 508320,
    "end": 509000
  },
  {
    "word": "لنكون",
    "start": 509000,
    "end": 510000
  },
  {
    "word": "من",
    "start": 510000,
    "end": 511700
  },
  {
    "word": "الخاسرين",
    "start": 511700,
    "end": 514100
  },
  {
    "word": "ولما",
    "start": 515100,
    "end": 516440
  },
  {
    "word": "رجع",
    "start": 516440,
    "end": 517799
  },
  {
    "word": "موسى",
    "start": 517799,
    "end": 518820
  },
  {
    "word": "إلى",
    "start": 518820,
    "end": 519280
  },
  {
    "word": "قومه",
    "start": 519280,
    "end": 520460
  },
  {
    "word": "غبان",
    "start": 520460,
    "end": 522020
  },
  {
    "word": "أسفاء",
    "start": 522020,
    "end": 523320
  },
  {
    "word": "قال",
    "start": 524320,
    "end": 525440
  },
  {
    "word": "بئس",
    "start": 525440,
    "end": 526080
  },
  {
    "word": "ما",
    "start": 526080,
    "end": 526520
  },
  {
    "word": "خلفتموني",
    "start": 526520,
    "end": 528600
  },
  {
    "word": "من",
    "start": 528600,
    "end": 529200
  },
  {
    "word": "بعده",
    "start": 529200,
    "end": 531520
  },
  {
    "word": "أعجلتموا",
    "start": 533260,
    "end": 534660
  },
  {
    "word": "أمر",
    "start": 534660,
    "end": 535200
  },
  {
    "word": "ربكم",
    "start": 535200,
    "end": 536280
  },
  {
    "word": "وألقى",
    "start": 536280,
    "end": 537520
  },
  {
    "word": "الألواح",
    "start": 537520,
    "end": 538760
  },
  {
    "word": "وأخذ",
    "start": 538760,
    "end": 539620
  },
  {
    "word": "برأس",
    "start": 539620,
    "end": 540560
  },
  {
    "word": "أخيه",
    "start": 540560,
    "end": 541700
  },
  {
    "word": "يجره",
    "start": 541700,
    "end": 542960
  },
  {
    "word": "إليه",
    "start": 542960,
    "end": 544760
  },
  {
    "word": "قال",
    "start": 545640,
    "end": 546340
  },
  {
    "word": "بنا",
    "start": 546340,
    "end": 547000
  },
  {
    "word": "أم",
    "start": 547000,
    "end": 548420
  },
  {
    "word": "إن",
    "start": 548420,
    "end": 549100
  },
  {
    "word": "القوم",
    "start": 549100,
    "end": 550740
  },
  {
    "word": "استضعفوني",
    "start": 550740,
    "end": 552760
  },
  {
    "word": "وكادوا",
    "start": 552760,
    "end": 554180
  },
  {
    "word": "يقتلونني",
    "start": 554180,
    "end": 556160
  },
  {
    "word": "فلا",
    "start": 556760,
    "end": 558140
  },
  {
    "word": "تشمت",
    "start": 558140,
    "end": 559020
  },
  {
    "word": "بي",
    "start": 559020,
    "end": 559460
  },
  {
    "word": "الأعداء",
    "start": 559460,
    "end": 562140
  },
  {
    "word": "ولا",
    "start": 562140,
    "end": 562860
  },
  {
    "word": "تجعلني",
    "start": 562860,
    "end": 564640
  },
  {
    "word": "مع",
    "start": 564640,
    "end": 565080
  },
  {
    "word": "القوم",
    "start": 565080,
    "end": 566100
  },
  {
    "word": "الظالمين",
    "start": 566100,
    "end": 568500
  },
  {
    "word": "قال",
    "start": 569500,
    "end": 570440
  },
  {
    "word": "رب",
    "start": 570440,
    "end": 571200
  },
  {
    "word": "غفذ",
    "start": 571200,
    "end": 572000
  },
  {
    "word": "لي",
    "start": 572000,
    "end": 572460
  },
  {
    "word": "ولأخي",
    "start": 572460,
    "end": 578840
  },
  {
    "word": "وأدخلنا",
    "start": 578840,
    "end": 580480
  },
  {
    "word": "في",
    "start": 580480,
    "end": 580880
  },
  {
    "word": "رحمتك",
    "start": 580880,
    "end": 582260
  },
  {
    "word": "وأنت",
    "start": 582260,
    "end": 584280
  },
  {
    "word": "أضحم",
    "start": 584280,
    "end": 585260
  },
  {
    "word": "الظاحمين",
    "start": 585260,
    "end": 588140
  },
  {
    "word": "إن",
    "start": 589140,
    "end": 590180
  },
  {
    "word": "الذين",
    "start": 590180,
    "end": 591540
  },
  {
    "word": "اتخذوا",
    "start": 591540,
    "end": 592420
  },
  {
    "word": "العجلس",
    "start": 592420,
    "end": 593220
  },
  {
    "word": "ينالهم",
    "start": 593220,
    "end": 594440
  },
  {
    "word": "غضب",
    "start": 594440,
    "end": 595540
  },
  {
    "word": "من",
    "start": 595540,
    "end": 596620
  },
  {
    "word": "ربهم",
    "start": 596620,
    "end": 597900
  },
  {
    "word": "وذلة",
    "start": 597900,
    "end": 599240
  },
  {
    "word": "في",
    "start": 599240,
    "end": 600460
  },
  {
    "word": "الحياة",
    "start": 600460,
    "end": 601560
  },
  {
    "word": "الدنيا",
    "start": 601560,
    "end": 603140
  },
  {
    "word": "وكذلك",
    "start": 603140,
    "end": 605680
  },
  {
    "word": "نجز",
    "start": 605680,
    "end": 606360
  },
  {
    "word": "المفترين",
    "start": 606360,
    "end": 608280
  },
  {
    "word": "والذين",
    "start": 609280,
    "end": 610880
  },
  {
    "word": "عملوا",
    "start": 610880,
    "end": 611480
  },
  {
    "word": "السيئات",
    "start": 611480,
    "end": 612760
  },
  {
    "word": "ثم",
    "start": 612760,
    "end": 613400
  },
  {
    "word": "تابوا",
    "start": 613400,
    "end": 614860
  },
  {
    "word": "من",
    "start": 614860,
    "end": 615400
  },
  {
    "word": "بعدها",
    "start": 615400,
    "end": 616880
  },
  {
    "word": "وآمنوا",
    "start": 616880,
    "end": 618380
  },
  {
    "word": "إن",
    "start": 618380,
    "end": 620220
  },
  {
    "word": "ربك",
    "start": 620220,
    "end": 621760
  },
  {
    "word": "من",
    "start": 621760,
    "end": 622240
  },
  {
    "word": "بعدها",
    "start": 622240,
    "end": 623800
  },
  {
    "word": "لغفور",
    "start": 623800,
    "end": 625060
  },
  {
    "word": "الرحيم",
    "start": 625060,
    "end": 627020
  },
  {
    "word": "ولما",
    "start": 628020,
    "end": 629580
  },
  {
    "word": "سكت",
    "start": 629580,
    "end": 630980
  },
  {
    "word": "عن",
    "start": 630980,
    "end": 631420
  },
  {
    "word": "موسى",
    "start": 631420,
    "end": 632820
  },
  {
    "word": "الغضب",
    "start": 632820,
    "end": 633540
  },
  {
    "word": "أخذ",
    "start": 633540,
    "end": 634220
  },
  {
    "word": "الألواح",
    "start": 634220,
    "end": 639700
  },
  {
    "word": "وفي",
    "start": 639700,
    "end": 640380
  },
  {
    "word": "نسختها",
    "start": 640380,
    "end": 641800
  },
  {
    "word": "هدوء",
    "start": 641800,
    "end": 643280
  },
  {
    "word": "ورحمة",
    "start": 643280,
    "end": 648500
  },
  {
    "word": "للذين",
    "start": 648500,
    "end": 650860
  },
  {
    "word": "هموا",
    "start": 650860,
    "end": 651680
  },
  {
    "word": "لربهم",
    "start": 651680,
    "end": 652980
  },
  {
    "word": "يرهبون",
    "start": 652980,
    "end": 655340
  },
  {
    "word": "واختار",
    "start": 656340,
    "end": 657560
  },
  {
    "word": "موسى",
    "start": 657560,
    "end": 658440
  },
  {
    "word": "قومه",
    "start": 658440,
    "end": 659360
  },
  {
    "word": "70",
    "start": 659360,
    "end": 660060
  },
  {
    "word": "رجلاً",
    "start": 660060,
    "end": 661500
  },
  {
    "word": "لميقاتنا",
    "start": 661500,
    "end": 663380
  },
  {
    "word": "فلما",
    "start": 664940,
    "end": 666340
  },
  {
    "word": "أخذتهم",
    "start": 666340,
    "end": 667700
  },
  {
    "word": "الرجفة",
    "start": 667700,
    "end": 668800
  },
  {
    "word": "قال",
    "start": 668800,
    "end": 669280
  },
  {
    "word": "رب",
    "start": 669280,
    "end": 669920
  },
  {
    "word": "لو",
    "start": 669920,
    "end": 670360
  },
  {
    "word": "شئت",
    "start": 670360,
    "end": 671020
  },
  {
    "word": "أهلكتهم",
    "start": 671020,
    "end": 672500
  },
  {
    "word": "من",
    "start": 672500,
    "end": 673260
  },
  {
    "word": "قبل",
    "start": 673260,
    "end": 674480
  },
  {
    "word": "وإياي",
    "start": 674480,
    "end": 676800
  },
  {
    "word": "أتهلكنا",
    "start": 678260,
    "end": 679660
  },
  {
    "word": "بما",
    "start": 679660,
    "end": 680180
  },
  {
    "word": "فعل",
    "start": 680180,
    "end": 680720
  },
  {
    "word": "السفاء",
    "start": 680720,
    "end": 682460
  },
  {
    "word": "مننا",
    "start": 682460,
    "end": 685440
  },
  {
    "word": "إن",
    "start": 685440,
    "end": 687240
  },
  {
    "word": "هي",
    "start": 687240,
    "end": 687520
  },
  {
    "word": "إلا",
    "start": 687520,
    "end": 688180
  },
  {
    "word": "فتنتك",
    "start": 688180,
    "end": 689240
  },
  {
    "word": "تضل",
    "start": 689240,
    "end": 689920
  },
  {
    "word": "بها",
    "start": 689920,
    "end": 690620
  },
  {
    "word": "من",
    "start": 690620,
    "end": 691120
  },
  {
    "word": "تشاء",
    "start": 691120,
    "end": 693600
  },
  {
    "word": "وتهدي",
    "start": 693600,
    "end": 695020
  },
  {
    "word": "من",
    "start": 695020,
    "end": 695640
  },
  {
    "word": "تشاء",
    "start": 695640,
    "end": 698820
  },
  {
    "word": "أنت",
    "start": 699820,
    "end": 701580
  },
  {
    "word": "ولينا",
    "start": 701580,
    "end": 702560
  },
  {
    "word": "فغفر",
    "start": 702560,
    "end": 703660
  },
  {
    "word": "لنا",
    "start": 703660,
    "end": 704240
  },
  {
    "word": "ورحمنا",
    "start": 704240,
    "end": 712840
  },
  {
    "word": "وأنت",
    "start": 712840,
    "end": 714780
  },
  {
    "word": "خير",
    "start": 714780,
    "end": 715520
  },
  {
    "word": "الغافرين",
    "start": 715520,
    "end": 718760
  },
  {
    "word": "وكتب",
    "start": 719760,
    "end": 720760
  },
  {
    "word": "لنا",
    "start": 720760,
    "end": 721260
  },
  {
    "word": "في",
    "start": 721260,
    "end": 721660
  },
  {
    "word": "هذه",
    "start": 721660,
    "end": 722200
  },
  {
    "word": "الدنيا",
    "start": 722200,
    "end": 723440
  },
  {
    "word": "حسنة",
    "start": 723440,
    "end": 724340
  },
  {
    "word": "وفي",
    "start": 724340,
    "end": 725380
  },
  {
    "word": "الآخرة",
    "start": 725380,
    "end": 726580
  },
  {
    "word": "إن",
    "start": 726580,
    "end": 727600
  },
  {
    "word": "هدنا",
    "start": 727600,
    "end": 729180
  },
  {
    "word": "إليك",
    "start": 729180,
    "end": 730820
  },
  {
    "word": "قال",
    "start": 730820,
    "end": 732560
  },
  {
    "word": "عذاب",
    "start": 732560,
    "end": 733720
  },
  {
    "word": "أصيب",
    "start": 733720,
    "end": 734800
  },
  {
    "word": "به",
    "start": 734800,
    "end": 735300
  },
  {
    "word": "من",
    "start": 735300,
    "end": 735880
  },
  {
    "word": "أشاء",
    "start": 735880,
    "end": 737960
  },
  {
    "word": "ورحمتي",
    "start": 737960,
    "end": 739440
  },
  {
    "word": "وسعة",
    "start": 739440,
    "end": 740340
  },
  {
    "word": "كل",
    "start": 740340,
    "end": 740880
  },
  {
    "word": "شيء",
    "start": 740880,
    "end": 743420
  },
  {
    "word": "فسأكتبها",
    "start": 745100,
    "end": 746500
  },
  {
    "word": "للذين",
    "start": 746500,
    "end": 747860
  },
  {
    "word": "يتقون",
    "start": 747860,
    "end": 749240
  },
  {
    "word": "ويؤتون",
    "start": 749240,
    "end": 750520
  },
  {
    "word": "الزكات",
    "start": 750520,
    "end": 751660
  },
  {
    "word": "والذين",
    "start": 751660,
    "end": 752960
  },
  {
    "word": "هموا",
    "start": 752960,
    "end": 753860
  },
  {
    "word": "بآياتنا",
    "start": 753860,
    "end": 755560
  },
  {
    "word": "يؤمنون",
    "start": 755560,
    "end": 757480
  },
  {
    "word": "الذين",
    "start": 759180,
    "end": 760580
  },
  {
    "word": "يتبعون",
    "start": 760580,
    "end": 761800
  },
  {
    "word": "الرسول",
    "start": 761800,
    "end": 762740
  },
  {
    "word": "النبي",
    "start": 762740,
    "end": 764180
  },
  {
    "word": "الأمية",
    "start": 764180,
    "end": 766020
  },
  {
    "word": "الذي",
    "start": 766020,
    "end": 766600
  },
  {
    "word": "يجدونه",
    "start": 766600,
    "end": 768300
  },
  {
    "word": "مكتوباً",
    "start": 768300,
    "end": 775300
  },
  {
    "word": "عندهم",
    "start": 775300,
    "end": 775920
  },
  {
    "word": "في",
    "start": 775920,
    "end": 776660
  },
  {
    "word": "التورات",
    "start": 776660,
    "end": 777480
  },
  {
    "word": "والإنجيل",
    "start": 779080,
    "end": 780480
  },
  {
    "word": "يأمرهم",
    "start": 780480,
    "end": 781860
  },
  {
    "word": "بالمعروف",
    "start": 781860,
    "end": 783780
  },
  {
    "word": "وينهاهموا",
    "start": 783780,
    "end": 785640
  },
  {
    "word": "عن",
    "start": 785640,
    "end": 786000
  },
  {
    "word": "المنكر",
    "start": 786000,
    "end": 796760
  },
  {
    "word": "ويحل",
    "start": 796760,
    "end": 797880
  },
  {
    "word": "لهم",
    "start": 797880,
    "end": 798480
  },
  {
    "word": "الطيبات",
    "start": 798480,
    "end": 800140
  },
  {
    "word": "ويحذم",
    "start": 800140,
    "end": 801400
  },
  {
    "word": "عليهم",
    "start": 801400,
    "end": 802600
  },
  {
    "word": "الخبائف",
    "start": 802600,
    "end": 810760
  },
  {
    "word": "ويضعوا",
    "start": 811340,
    "end": 812720
  },
  {
    "word": "عنهم",
    "start": 812720,
    "end": 813100
  },
  {
    "word": "إصروم",
    "start": 813100,
    "end": 814760
  },
  {
    "word": "والأغلال",
    "start": 814760,
    "end": 816800
  },
  {
    "word": "التي",
    "start": 816800,
    "end": 817580
  },
  {
    "word": "كانت",
    "start": 817580,
    "end": 818880
  },
  {
    "word": "عليهم",
    "start": 818880,
    "end": 820180
  },
  {
    "word": "فالذين",
    "start": 820180,
    "end": 822460
  },
  {
    "word": "آمنوا",
    "start": 822460,
    "end": 823600
  },
  {
    "word": "به",
    "start": 823600,
    "end": 824060
  },
  {
    "word": "وعزرواه",
    "start": 824060,
    "end": 826200
  },
  {
    "word": "ونصرواه",
    "start": 826200,
    "end": 828500
  },
  {
    "word": "واتبعوا",
    "start": 828500,
    "end": 829680
  },
  {
    "word": "النور",
    "start": 829680,
    "end": 834600
  },
  {
    "word": "الذي",
    "start": 834600,
    "end": 835140
  },
  {
    "word": "أنزل",
    "start": 835140,
    "end": 837240
  },
  {
    "word": "معه",
    "start": 837240,
    "end": 838280
  },
  {
    "word": "أولئك",
    "start": 838280,
    "end": 840900
  },
  {
    "word": "هم",
    "start": 840900,
    "end": 841260
  },
  {
    "word": "المفلحون",
    "start": 841260,
    "end": 843340
  },
  {
    "word": "قل",
    "start": 844340,
    "end": 845180
  },
  {
    "word": "يا",
    "start": 845180,
    "end": 845540
  },
  {
    "word": "أيها",
    "start": 845540,
    "end": 846340
  },
  {
    "word": "الناس",
    "start": 846340,
    "end": 847560
  },
  {
    "word": "إني",
    "start": 847560,
    "end": 848640
  },
  {
    "word": "رسول",
    "start": 848640,
    "end": 849660
  },
  {
    "word": "الله",
    "start": 849660,
    "end": 850460
  },
  {
    "word": "إليكم",
    "start": 850460,
    "end": 851920
  },
  {
    "word": "جميعا",
    "start": 851920,
    "end": 854000
  },
  {
    "word": "الذي",
    "start": 854000,
    "end": 855960
  },
  {
    "word": "لهم",
    "start": 855960,
    "end": 856760
  },
  {
    "word": "الكسماوات",
    "start": 856760,
    "end": 858700
  },
  {
    "word": "والأرض",
    "start": 858700,
    "end": 859760
  },
  {
    "word": "لا",
    "start": 859760,
    "end": 860340
  },
  {
    "word": "إله",
    "start": 860340,
    "end": 861220
  },
  {
    "word": "إلا",
    "start": 861220,
    "end": 862200
  },
  {
    "word": "هو",
    "start": 862200,
    "end": 862680
  },
  {
    "word": "يحيي",
    "start": 862680,
    "end": 863800
  },
  {
    "word": "ويوميت",
    "start": 863800,
    "end": 865820
  },
  {
    "word": "فآمنوا",
    "start": 866820,
    "end": 868060
  },
  {
    "word": "بالله",
    "start": 868060,
    "end": 869020
  },
  {
    "word": "ورسوله",
    "start": 869020,
    "end": 874160
  },
  {
    "word": "النبي",
    "start": 874160,
    "end": 876700
  },
  {
    "word": "الأمي",
    "start": 876700,
    "end": 878980
  },
  {
    "word": "الذي",
    "start": 878980,
    "end": 879540
  },
  {
    "word": "يؤمن",
    "start": 879540,
    "end": 880740
  },
  {
    "word": "بالله",
    "start": 880740,
    "end": 882020
  },
  {
    "word": "وكلماته",
    "start": 882020,
    "end": 884220
  },
  {
    "word": "فآمنوا",
    "start": 884220,
    "end": 886560
  },
  {
    "word": "بالله",
    "start": 886560,
    "end": 887300
  },
  {
    "word": "ورسوله",
    "start": 887300,
    "end": 888560
  },
  {
    "word": "النبي",
    "start": 888560,
    "end": 889700
  },
  {
    "word": "الأمي",
    "start": 889700,
    "end": 891780
  },
  {
    "word": "الذي",
    "start": 891780,
    "end": 892300
  },
  {
    "word": "يؤمن",
    "start": 892300,
    "end": 893380
  },
  {
    "word": "بالله",
    "start": 893380,
    "end": 894560
  },
  {
    "word": "وكلماته",
    "start": 894560,
    "end": 896520
  },
  {
    "word": "واتبعواه",
    "start": 896520,
    "end": 902040
  },
  {
    "word": "لعلكم",
    "start": 902040,
    "end": 903760
  },
  {
    "word": "تهتدون",
    "start": 903760,
    "end": 906800
  }
]